doc_curation/__init__.py
doc_curation/book_data.py
doc_curation/csv_to_yaml_md.py
doc_curation/tei.py
doc_curation/blog/__init__.py
doc_curation/blog/blogspot.py
doc_curation/blog/json_importer.py
doc_curation/blog/misc.py
doc_curation/blog/substack.py
doc_curation/blog/wordpress.py
doc_curation/ebook/__init__.py
doc_curation/ebook/convert.py
doc_curation/image/__init__.py
doc_curation/image/coordinate_geometry.py
doc_curation/image/svg-objects-export.py
doc_curation/image/svg_helper.py
doc_curation/image/tikz.py
doc_curation/mail_stream/__init__.py
doc_curation/mail_stream/google_groups.py
doc_curation/mail_stream/mailman.py
doc_curation/md/__init__.py
doc_curation/md/file.py
doc_curation/md/content_processor/__init__.py
doc_curation/md/content_processor/ambuda_helper.py
doc_curation/md/content_processor/commentary_helper.py
doc_curation/md/content_processor/details_helper.py
doc_curation/md/content_processor/embed_helper.py
doc_curation/md/content_processor/footnote_helper.py
doc_curation/md/content_processor/include_helper.py
doc_curation/md/content_processor/ocr_helper.py
doc_curation/md/content_processor/section_helper.py
doc_curation/md/content_processor/space_helper.py
doc_curation/md/content_processor/stripper.py
doc_curation/md/library/__init__.py
doc_curation/md/library/arrangement.py
doc_curation/md/library/combination.py
doc_curation/md/library/content_helper.py
doc_curation/md/library/metadata_helper.py
doc_curation/pdf/__init__.py
doc_curation/pdf/drive_ocr.py
doc_curation/pdf/google_vision_pdf.py
doc_curation/pdf/image_ops.py
doc_curation/pdf/kraken_ocr.py
doc_curation/pdf/removewatermark.py
doc_curation/pdf/data/__init__.py
doc_curation/scraping/__init__.py
doc_curation/scraping/html_scraper/__init__.py
doc_curation/scraping/html_scraper/css.py
doc_curation/scraping/html_scraper/selenium.py
doc_curation/scraping/html_scraper/souper.py
doc_curation/scraping/misc_sites/__init__.py
doc_curation/scraping/misc_sites/aadishilaa.py
doc_curation-0.1.20.dist-info/LICENSE.txt
doc_curation-0.1.20.dist-info/METADATA
doc_curation-0.1.20.dist-info/WHEEL
doc_curation-0.1.20.dist-info/top_level.txt
doc_curation-0.1.20.dist-info/RECORD
