Metadata-Version: 2.1
Name: doc-curation
Version: 0.1.20
Summary: A package for curating doc file collections, with ability to sync with youtube and archive.org doc items.
Home-page: https://github.com/sanskrit-coders/doc_curation
Author: Sanskrit programmers
Author-email: sanskrit-programmers@googlegroups.com
License: MIT
Keywords: documents books internet-archive
Platform: UNKNOWN
Classifier: Development Status :: 5 - Production/Stable
Classifier: Intended Audience :: Education
Classifier: Topic :: Text Processing :: Linguistic
Classifier: License :: OSI Approved :: MIT License
Classifier: Programming Language :: Python :: 3
Classifier: Programming Language :: Python :: 3.8
License-File: LICENSE.txt
Requires-Dist: curation-utils
Requires-Dist: indic-transliteration
Requires-Dist: wordcloud
Requires-Dist: urllib3
Requires-Dist: regex
Requires-Dist: pandas
Requires-Dist: requests
Requires-Dist: pytest
Requires-Dist: pypandoc
Requires-Dist: setuptools
Requires-Dist: bs4
Requires-Dist: beautifulsoup4
Requires-Dist: toml
Requires-Dist: yamldown-unicode
Requires-Dist: more-itertools
Requires-Dist: joblib
Requires-Dist: tqdm
Requires-Dist: roman
Requires-Dist: editdistance
Requires-Dist: datefinder
Provides-Extra: all
Requires-Dist: curation-utils ; extra == 'all'
Requires-Dist: indic-transliteration ; extra == 'all'
Requires-Dist: wordcloud ; extra == 'all'
Requires-Dist: urllib3 ; extra == 'all'
Requires-Dist: regex ; extra == 'all'
Requires-Dist: pandas ; extra == 'all'
Requires-Dist: requests ; extra == 'all'
Requires-Dist: pytest ; extra == 'all'
Requires-Dist: pypandoc ; extra == 'all'
Requires-Dist: setuptools ; extra == 'all'
Requires-Dist: bs4 ; extra == 'all'
Requires-Dist: beautifulsoup4 ; extra == 'all'
Requires-Dist: toml ; extra == 'all'
Requires-Dist: yamldown-unicode ; extra == 'all'
Requires-Dist: more-itertools ; extra == 'all'
Requires-Dist: joblib ; extra == 'all'
Requires-Dist: tqdm ; extra == 'all'
Requires-Dist: roman ; extra == 'all'
Requires-Dist: editdistance ; extra == 'all'
Requires-Dist: datefinder ; extra == 'all'
Requires-Dist: selenium ; extra == 'all'
Requires-Dist: google-cloud-vision ; extra == 'all'
Requires-Dist: kraken ; extra == 'all'
Requires-Dist: kraken[pdf] ; extra == 'all'
Requires-Dist: pikepdf ; extra == 'all'
Requires-Dist: pdf2image ; extra == 'all'
Requires-Dist: img2pdf ; extra == 'all'
Requires-Dist: lxml ; extra == 'all'
Requires-Dist: aksharamukha ; extra == 'all'
Provides-Extra: extras
Requires-Dist: editdistance ; extra == 'extras'
Requires-Dist: selenium ; extra == 'extras'
Requires-Dist: google-cloud-vision ; extra == 'extras'
Requires-Dist: kraken ; extra == 'extras'
Requires-Dist: kraken[pdf] ; extra == 'extras'
Requires-Dist: pikepdf ; extra == 'extras'
Requires-Dist: pdf2image ; extra == 'extras'
Requires-Dist: img2pdf ; extra == 'extras'
Requires-Dist: lxml ; extra == 'extras'
Requires-Dist: aksharamukha ; extra == 'extras'
Provides-Extra: test
Requires-Dist: pytest ; extra == 'test'
